{
  "version": "2.0.5",
  "description": "Market valuations for 20 O*NET Standard + 15 Unique Differentiator skills model",
  "lastUpdated": "2026-02-17",
  
  "skillBaseValues": {
    
    "_comment_onet_standard": "========== 20 O*NET STANDARD SKILLS (Industry Recognized) ==========",
    
    "_onet_critical_thinking": "Critical Thinking & Problem Solving (5 skills)",
    "Critical Thinking": 38000,
    "Complex Problem Solving": 42000,
    "Judgment and Decision Making": 40000,
    "Active Learning": 35000,
    "Systems Analysis": 40000,
    
    "_onet_communication": "Communication & Influence (6 skills)",
    "Speaking": 32000,
    "Writing": 30000,
    "Active Listening": 28000,
    "Persuasion": 36000,
    "Negotiation": 38000,
    "Social Perceptiveness": 32000,
    
    "_onet_leadership": "Leadership & Management (5 skills)",
    "Coordination": 35000,
    "Instructing": 30000,
    "Management of Personnel Resources": 40000,
    "Time Management": 28000,
    "Service Orientation": 30000,
    
    "_onet_strategy": "Strategy & Analysis (4 skills)",
    "Systems Evaluation": 38000,
    "Operations Analysis": 36000,
    "Learning Strategies": 32000,
    "Reading Comprehension": 25000,
    
    "_comment_unique": "========== 15 UNIQUE DIFFERENTIATORS (Specialized Expertise) ==========",
    
    "_unique_ai_tech": "AI & Technology Leadership (4 skills)",
    "Enterprise AI Strategy": 55000,
    "AI/ML Product Strategy": 50000,
    "Human-AI Collaboration Model Design": 45000,
    "Technical Concept Translation": 40000,
    
    "_unique_foresight": "Strategic Foresight (4 skills)",
    "Strategic Foresight & Market Prediction": 48000,
    "Predictive Framework Development": 44000,
    "Weak Signal Detection & Trend Recognition": 42000,
    "Research Synthesis & Pattern Recognition": 38000,
    
    "_unique_domain": "Domain Expertise (4 skills)",
    "HR Technology Market Intelligence": 40000,
    "Candidate Experience Architecture": 38000,
    "C-Suite Advisory & Influence": 46000,
    "Crisis Leadership & Decision Making": 45000,
    
    "_unique_capabilities": "Unique Capabilities (3 skills)",
    "Emergency Airmanship": 35000,
    "Spatial Reasoning & 3D Problem Solving": 36000,
    "Authentic Leadership & Trust Building": 38000
  },
  
  "proficiencyMultipliers": {
    "Mastery": 1.5,
    "Advanced": 1.3,
    "Proficient": 1.0
  },
  
  "locationMultipliers": {
    "San Francisco, CA": 1.25,
    "New York, NY": 1.20,
    "Seattle, WA": 1.18,
    "Boston, MA": 1.15,
    "Washington, DC": 1.12,
    "Los Angeles, CA": 1.10,
    "Chicago, IL": 1.08,
    "Philadelphia, PA": 1.05,
    "Austin, TX": 1.05,
    "Denver, CO": 1.03,
    "Remote": 1.00,
    "default": 1.00
  },
  
  "demandMultipliers": {
    "AI": 1.4,
    "Strategy": 1.25,
    "Leadership": 1.2,
    "Technology": 1.15,
    "default": 1.1
  },
  
  "roleBenchmarks": {
    "C-Suite": {
      "title": "C-Suite Executive",
      "marketRate50th": 320000,
      "requiredPoints": 24,
      "typicalSkills": ["Enterprise AI Strategy", "Critical Thinking", "Complex Problem Solving", "Strategic Foresight & Market Prediction", "Judgment and Decision Making"]
    },
    "VP/Senior Director": {
      "title": "VP / Senior Director",
      "marketRate50th": 245000,
      "requiredPoints": 15,
      "typicalSkills": ["Complex Problem Solving", "Systems Analysis", "Persuasion", "Management of Personnel Resources", "Strategic Foresight & Market Prediction"]
    },
    "Director/Senior": {
      "title": "Director / Senior Manager",
      "marketRate50th": 160000,
      "requiredPoints": 10,
      "typicalSkills": ["Critical Thinking", "Coordination", "Operations Analysis", "Negotiation"]
    },
    "Mid-Level": {
      "title": "Mid-Level Professional",
      "marketRate50th": 95000,
      "requiredPoints": 6,
      "typicalSkills": ["Active Learning", "Speaking", "Writing", "Time Management"]
    },
    "Entry": {
      "title": "Entry / Junior",
      "marketRate50th": 65000,
      "requiredPoints": 0,
      "typicalSkills": ["Reading Comprehension", "Active Listening", "Service Orientation"]
    }
  },
  
  "calculationNotes": {
    "methodology": "Top 10 skills → Calculate points → Determine role tier → Apply premiums → Location adjustment",
    "pointsSystem": "Mastery=3pts, Advanced=2pts, Proficient=1pt",
    "premiumsCap": "Maximum 25% total premiums (domain + rarity)",
    "rarityBonus": "Maximum 15% for unique skill combinations",
    "expectedAccuracy": "Within 5% of actual market compensation"
  },
  
  "testCase_Cliff": {
    "description": "Validation test: Cliff's profile should yield ~$320k",
    "top10Skills": [
      {"skill": "Enterprise AI Strategy", "level": "Mastery", "baseValue": 55000},
      {"skill": "AI/ML Product Strategy", "level": "Mastery", "baseValue": 50000},
      {"skill": "Strategic Foresight & Market Prediction", "level": "Mastery", "baseValue": 48000},
      {"skill": "C-Suite Advisory & Influence", "level": "Advanced", "baseValue": 46000},
      {"skill": "Human-AI Collaboration Model Design", "level": "Mastery", "baseValue": 45000},
      {"skill": "Crisis Leadership & Decision Making", "level": "Mastery", "baseValue": 45000},
      {"skill": "Predictive Framework Development", "level": "Mastery", "baseValue": 44000},
      {"skill": "Complex Problem Solving", "level": "Mastery", "baseValue": 42000},
      {"skill": "Weak Signal Detection & Trend Recognition", "level": "Mastery", "baseValue": 42000},
      {"skill": "Technical Concept Translation", "level": "Mastery", "baseValue": 40000}
    ],
    "skillPoints": 27,
    "roleLevel": "VP/Senior Director",
    "marketRate": 245000,
    "aiPremium": 0.15,
    "rarityBonus": 0.08,
    "locationMultiplier": 1.05,
    "expectedWorth": 320000,
    "actualWorth": 300000,
    "accuracy": "94%"
  }
}
